odoo9_addon_account_multicurrency_revaluation-9.0.1.0.0.99.dev29-py3.8-nspkg.pth
odoo_addons/account_multicurrency_revaluation/README.rst
odoo_addons/account_multicurrency_revaluation/__init__.py
odoo_addons/account_multicurrency_revaluation/__openerp__.py
odoo_addons/account_multicurrency_revaluation/demo/account_demo.xml
odoo_addons/account_multicurrency_revaluation/demo/currency_demo.xml
odoo_addons/account_multicurrency_revaluation/i18n/account_multicurrency_revaluation.pot
odoo_addons/account_multicurrency_revaluation/i18n/am.po
odoo_addons/account_multicurrency_revaluation/i18n/ar.po
odoo_addons/account_multicurrency_revaluation/i18n/bg.po
odoo_addons/account_multicurrency_revaluation/i18n/bs.po
odoo_addons/account_multicurrency_revaluation/i18n/ca.po
odoo_addons/account_multicurrency_revaluation/i18n/ca_ES.po
odoo_addons/account_multicurrency_revaluation/i18n/cs.po
odoo_addons/account_multicurrency_revaluation/i18n/da.po
odoo_addons/account_multicurrency_revaluation/i18n/de.po
odoo_addons/account_multicurrency_revaluation/i18n/el_GR.po
odoo_addons/account_multicurrency_revaluation/i18n/en_AU.po
odoo_addons/account_multicurrency_revaluation/i18n/en_GB.po
odoo_addons/account_multicurrency_revaluation/i18n/es.po
odoo_addons/account_multicurrency_revaluation/i18n/es_AR.po
odoo_addons/account_multicurrency_revaluation/i18n/es_CL.po
odoo_addons/account_multicurrency_revaluation/i18n/es_CO.po
odoo_addons/account_multicurrency_revaluation/i18n/es_CR.po
odoo_addons/account_multicurrency_revaluation/i18n/es_DO.po
odoo_addons/account_multicurrency_revaluation/i18n/es_EC.po
odoo_addons/account_multicurrency_revaluation/i18n/es_ES.po
odoo_addons/account_multicurrency_revaluation/i18n/es_MX.po
odoo_addons/account_multicurrency_revaluation/i18n/es_PE.po
odoo_addons/account_multicurrency_revaluation/i18n/es_PY.po
odoo_addons/account_multicurrency_revaluation/i18n/es_VE.po
odoo_addons/account_multicurrency_revaluation/i18n/et.po
odoo9_addon_account_multicurrency_revaluation-9.0.1.0.0.99.dev29.dist-info/METADATA
odoo9_addon_account_multicurrency_revaluation-9.0.1.0.0.99.dev29.dist-info/WHEEL
odoo9_addon_account_multicurrency_revaluation-9.0.1.0.0.99.dev29.dist-info/namespace_packages.txt
odoo9_addon_account_multicurrency_revaluation-9.0.1.0.0.99.dev29.dist-info/top_level.txt
odoo9_addon_account_multicurrency_revaluation-9.0.1.0.0.99.dev29.dist-info/RECORD
